ZAminofix/__init__.py
ZAminofix/acm.py
ZAminofix/client.py
ZAminofix/socket.py
ZAminofix/sub_client.py
ZAminofix/lib/__init__.py
ZAminofix/lib/util/__init__.py
ZAminofix/lib/util/exceptions.py
ZAminofix/lib/util/headers.py
ZAminofix/lib/util/helpers.py
ZAminofix/lib/util/objects.py
sorex-0.5.0.dist-info/licenses/LICENSE
sorex-0.5.0.dist-info/METADATA
sorex-0.5.0.dist-info/WHEEL
sorex-0.5.0.dist-info/top_level.txt
sorex-0.5.0.dist-info/RECORD
