Metadata-Version: 2.4
Name: Sorex
Version: 0.5.0
Summary: By Sor. https://t.me/Tearedeyes
Author: Sor
Keywords: ZAmino,ZAmino.fix,aminoapps,ZAminofix,amino,amino-bot
Requires-Python: >=3.6
License-File: LICENSE
Requires-Dist: httpx
Requires-Dist: websocket-client==1.3.1
Requires-Dist: setuptools
Requires-Dist: json_minify
Requires-Dist: six
Requires-Dist: aiohttp
Requires-Dist: websockets
Requires-Dist: colorama
Dynamic: author
Dynamic: description
Dynamic: keywords
Dynamic: license-file
Dynamic: requires-dist
Dynamic: requires-python
Dynamic: summary
